LICENSE
MANIFEST.in
README.md
requirements.txt
setup.py
bnlcrl/__init__.py
bnlcrl/base_pkconfig.py
bnlcrl/bnlcrl_console.py
bnlcrl/crl_simulator.py
bnlcrl/delta_finder.py
bnlcrl/plot_delta.py
bnlcrl/utils.py
bnlcrl/visualize.py
bnlcrl.egg-info/PKG-INFO
bnlcrl.egg-info/SOURCES.txt
bnlcrl.egg-info/dependency_links.txt
bnlcrl.egg-info/entry_points.txt
bnlcrl.egg-info/requires.txt
bnlcrl.egg-info/top_level.txt
bnlcrl/package_data/.gitignore
bnlcrl/package_data/cli_function.jinja
bnlcrl/package_data/dat/Al_atten.dat
bnlcrl/package_data/dat/Al_delta.dat
bnlcrl/package_data/dat/Au_atten.dat
bnlcrl/package_data/dat/Au_delta.dat
bnlcrl/package_data/dat/B_atten.dat
bnlcrl/package_data/dat/B_delta.dat
bnlcrl/package_data/dat/Be_atten.dat
bnlcrl/package_data/dat/Be_delta.dat
bnlcrl/package_data/dat/C_atten.dat
bnlcrl/package_data/dat/C_delta.dat
bnlcrl/package_data/dat/Cu_atten.dat
bnlcrl/package_data/dat/Cu_delta.dat
bnlcrl/package_data/dat/Li_atten.dat
bnlcrl/package_data/dat/Li_delta.dat
bnlcrl/package_data/dat/Mo_atten.dat
bnlcrl/package_data/dat/Mo_delta.dat
bnlcrl/package_data/dat/SiO2_atten.dat
bnlcrl/package_data/dat/SiO2_delta.dat
bnlcrl/package_data/dat/Si_atten.dat
bnlcrl/package_data/dat/Si_delta.dat
bnlcrl/package_data/dat/W_atten.dat
bnlcrl/package_data/dat/W_delta.dat
bnlcrl/package_data/json/defaults_crl.json
bnlcrl/package_data/json/defaults_delta.json
bnlcrl/package_data/json/smi_crl.json
bnlcrl/pkcli/__init__.py
bnlcrl/pkcli/simulate.py
docs/.gitignore
docs/Kuhlmann_Marion.pdf
docs/attenuation_filters.png
docs/bnlcrl.pkcli.rst
docs/bnlcrl.rst
docs/conf.py
docs/index.rst
docs/modules.rst
docs/transfocator.png
docs/_static/.gitignore
docs/_templates/.gitignore
tests/.gitignore
tests/conftest.py
tests/utils_test.py
tests/pkcli/simulate_test.py